LICENSE
MANIFEST.in
README.md
setup.py
django_madmin/__init__.py
django_madmin/admin.py
django_madmin/models.py
django_madmin/urls.py
django_madmin/views.py
django_madmin/widgets.py
django_madmin.egg-info/PKG-INFO
django_madmin.egg-info/SOURCES.txt
django_madmin.egg-info/dependency_links.txt
django_madmin.egg-info/requires.txt
django_madmin.egg-info/top_level.txt
django_madmin/static/.DS_Store
django_madmin/static/madmin/.DS_Store
django_madmin/static/madmin/js/.DS_Store
django_madmin/static/madmin/js/index-875e457d.js
django_madmin/static/madmin/js/tailwindcss.min.js
django_madmin/templates/admin/base_site.html
django_madmin/templates/admin/m_change_list.html
django_madmin/templates/admin/m_filter.html
django_madmin/templates/madmin/vue_component.html